django_form_copy
