Metadata-Version: 2.1
Name: django-form-copy
Version: 0.1.6
Summary: Library for quickly copying django objects from one to another project.
Home-page: https://github.com/DeNRuDi/django-form-copy
Author: DeNRuDi
Author-email: denisrudnitskiy0@gmail.com
Classifier: Development Status :: 4 - Beta
Classifier: Intended Audience :: Developers
Classifier: Operating System :: OS Independent
Classifier: License :: OSI Approved :: BSD License
Classifier: Programming Language :: Python :: 3
Classifier: Programming Language :: Python :: 3.7
Classifier: Programming Language :: Python :: 3.8
Classifier: Programming Language :: Python :: 3.9
Classifier: Programming Language :: Python :: 3.10
Classifier: Programming Language :: Python :: 3.11
License-File: LICENSE
Requires-Dist: django
Requires-Dist: clipboard==0.0.4
Requires-Dist: python-dateutil==2.8.2
